{
  "bans": {
    "Gwen": {
      "bans": 1571,
      "bans_weighted": 2190.0,
      "ban_rate": 4.9308,
      "ban_rate_weighted": 4.7893
    },
    "Zed": {
      "bans": 14390,
      "bans_weighted": 20312.0,
      "ban_rate": 45.1649,
      "ban_rate_weighted": 44.4201
    },
    "Irelia": {
      "bans": 3948,
      "bans_weighted": 5573.0,
      "ban_rate": 12.3913,
      "ban_rate_weighted": 12.1875
    },
    "Karma": {
      "bans": 4691,
      "bans_weighted": 6593.0,
      "ban_rate": 14.7233,
      "ban_rate_weighted": 14.4182
    },
    "Riven": {
      "bans": 3529,
      "bans_weighted": 5063.0,
      "ban_rate": 11.0762,
      "ban_rate_weighted": 11.0722
    },
    "Rengar": {
      "bans": 15544,
      "bans_weighted": 23225.0,
      "ban_rate": 48.7869,
      "ban_rate_weighted": 50.7906
    },
    "Kassadin": {
      "bans": 5900,
      "bans_weighted": 8250.0,
      "ban_rate": 18.5179,
      "ban_rate_weighted": 18.0419
    },
    "Jax": {
      "bans": 7296,
      "bans_weighted": 10937.0,
      "ban_rate": 22.8995,
      "ban_rate_weighted": 23.918
    },
    "Pyke": {
      "bans": 10871,
      "bans_weighted": 16262.0,
      "ban_rate": 34.1201,
      "ban_rate_weighted": 35.5632
    },
    "Yorick": {
      "bans": 2613,
      "bans_weighted": 3710.0,
      "ban_rate": 8.2012,
      "ban_rate_weighted": 8.1134
    },
    "Malphite": {
      "bans": 2659,
      "bans_weighted": 3978.0,
      "ban_rate": 8.3456,
      "ban_rate_weighted": 8.6995
    },
    "Urgot": {
      "bans": 57,
      "bans_weighted": 81.0,
      "ban_rate": 0.1789,
      "ban_rate_weighted": 0.1771
    },
    "Sylas": {
      "bans": 2900,
      "bans_weighted": 3988.0,
      "ban_rate": 9.102,
      "ban_rate_weighted": 8.7213
    },
    "Qiyana": {
      "bans": 14901,
      "bans_weighted": 21760.0,
      "ban_rate": 46.7688,
      "ban_rate_weighted": 47.5868
    },
    "Ashe": {
      "bans": 882,
      "bans_weighted": 1319.0,
      "ban_rate": 2.7683,
      "ban_rate_weighted": 2.8845
    },
    "Karthus": {
      "bans": 1986,
      "bans_weighted": 2869.0,
      "ban_rate": 6.2333,
      "ban_rate_weighted": 6.2742
    },
    "Kayn": {
      "bans": 5030,
      "bans_weighted": 7118.0,
      "ban_rate": 15.7873,
      "ban_rate_weighted": 15.5663
    },
    "Fiddlesticks": {
      "bans": 295,
      "bans_weighted": 421.0,
      "ban_rate": 0.9259,
      "ban_rate_weighted": 0.9207
    },
    "Nautilus": {
      "bans": 4915,
      "bans_weighted": 6845.0,
      "ban_rate": 15.4264,
      "ban_rate_weighted": 14.9693
    },
    "Kai'Sa": {
      "bans": 1448,
      "bans_weighted": 2264.0,
      "ban_rate": 4.5447,
      "ban_rate_weighted": 4.9511
    },
    "Lucian": {
      "bans": 3206,
      "bans_weighted": 4685.0,
      "ban_rate": 10.0625,
      "ban_rate_weighted": 10.2456
    },
    "Katarina": {
      "bans": 5162,
      "bans_weighted": 7829.0,
      "ban_rate": 16.2016,
      "ban_rate_weighted": 17.1212
    },
    "Draven": {
      "bans": 3333,
      "bans_weighted": 5187.0,
      "ban_rate": 10.4611,
      "ban_rate_weighted": 11.3434
    },
    "Kayle": {
      "bans": 1026,
      "bans_weighted": 1721.0,
      "ban_rate": 3.2202,
      "ban_rate_weighted": 3.7636
    },
    "Vladimir": {
      "bans": 9644,
      "bans_weighted": 13761.0,
      "ban_rate": 30.269,
      "ban_rate_weighted": 30.0938
    },
    "Yasuo": {
      "bans": 8618,
      "bans_weighted": 12127.0,
      "ban_rate": 27.0487,
      "ban_rate_weighted": 26.5204
    },
    "Fiora": {
      "bans": 4365,
      "bans_weighted": 6252.0,
      "ban_rate": 13.7001,
      "ban_rate_weighted": 13.6724
    },
    "Aphelios": {
      "bans": 513,
      "bans_weighted": 744.0,
      "ban_rate": 1.6101,
      "ban_rate_weighted": 1.627
    },
    "Master Yi": {
      "bans": 13511,
      "bans_weighted": 19035.0,
      "ban_rate": 42.4061,
      "ban_rate_weighted": 41.6275
    },
    "Mel": {
      "bans": 6664,
      "bans_weighted": 9864.0,
      "ban_rate": 20.9159,
      "ban_rate_weighted": 21.5715
    },
    "Lulu": {
      "bans": 3698,
      "bans_weighted": 5062.0,
      "ban_rate": 11.6067,
      "ban_rate_weighted": 11.07
    },
    "Wukong": {
      "bans": 1818,
      "bans_weighted": 2673.0,
      "ban_rate": 5.706,
      "ban_rate_weighted": 5.8456
    },
    "Nidalee": {
      "bans": 278,
      "bans_weighted": 360.0,
      "ban_rate": 0.8725,
      "ban_rate_weighted": 0.7873
    },
    "Lux": {
      "bans": 1011,
      "bans_weighted": 1277.0,
      "ban_rate": 3.1732,
      "ban_rate_weighted": 2.7927
    },
    "Renekton": {
      "bans": 2877,
      "bans_weighted": 4063.0,
      "ban_rate": 9.0298,
      "ban_rate_weighted": 8.8853
    },
    "Poppy": {
      "bans": 2005,
      "bans_weighted": 2985.0,
      "ban_rate": 6.293,
      "ban_rate_weighted": 6.5279
    },
    "Akali": {
      "bans": 3601,
      "bans_weighted": 5128.0,
      "ban_rate": 11.3022,
      "ban_rate_weighted": 11.2144
    },
    "Nami": {
      "bans": 861,
      "bans_weighted": 1164.0,
      "ban_rate": 2.7024,
      "ban_rate_weighted": 2.5455
    },
    "LeBlanc": {
      "bans": 7013,
      "bans_weighted": 10658.0,
      "ban_rate": 22.0112,
      "ban_rate_weighted": 23.3079
    },
    "Ambessa": {
      "bans": 4148,
      "bans_weighted": 5793.0,
      "ban_rate": 13.0191,
      "ban_rate_weighted": 12.6687
    },
    "Aurora": {
      "bans": 3691,
      "bans_weighted": 5458.0,
      "ban_rate": 11.5847,
      "ban_rate_weighted": 11.9361
    },
    "Bel'Veth": {
      "bans": 564,
      "bans_weighted": 814.0,
      "ban_rate": 1.7702,
      "ban_rate_weighted": 1.7801
    },
    "Bardo": {
      "bans": 929,
      "bans_weighted": 1322.0,
      "ban_rate": 2.9158,
      "ban_rate_weighted": 2.8911
    },
    "Talon": {
      "bans": 4405,
      "bans_weighted": 6256.0,
      "ban_rate": 13.8257,
      "ban_rate_weighted": 13.6812
    },
    "Quinn": {
      "bans": 2074,
      "bans_weighted": 3255.0,
      "ban_rate": 6.5095,
      "ban_rate_weighted": 7.1183
    },
    "Sivir": {
      "bans": 1469,
      "bans_weighted": 2021.0,
      "ban_rate": 4.6107,
      "ban_rate_weighted": 4.4197
    },
    "Jayce": {
      "bans": 2785,
      "bans_weighted": 3937.0,
      "ban_rate": 8.7411,
      "ban_rate_weighted": 8.6098
    },
    "Mordekaiser": {
      "bans": 833,
      "bans_weighted": 1065.0,
      "ban_rate": 2.6145,
      "ban_rate_weighted": 2.329
    },
    "Kha'Zix": {
      "bans": 1032,
      "bans_weighted": 1437.0,
      "ban_rate": 3.2391,
      "ban_rate_weighted": 3.1426
    },
    "Hwei": {
      "bans": 607,
      "bans_weighted": 837.0,
      "ban_rate": 1.9052,
      "ban_rate_weighted": 1.8304
    },
    "Pantheon": {
      "bans": 866,
      "bans_weighted": 1123.0,
      "ban_rate": 2.7181,
      "ban_rate_weighted": 2.4559
    },
    "Volibear": {
      "bans": 1422,
      "bans_weighted": 1766.0,
      "ban_rate": 4.4631,
      "ban_rate_weighted": 3.8621
    },
    "Leona": {
      "bans": 348,
      "bans_weighted": 464.0,
      "ban_rate": 1.0922,
      "ban_rate_weighted": 1.0147
    },
    "Ekko": {
      "bans": 2622,
      "bans_weighted": 3855.0,
      "ban_rate": 8.2295,
      "ban_rate_weighted": 8.4305
    },
    "Vayne": {
      "bans": 880,
      "bans_weighted": 1188.0,
      "ban_rate": 2.762,
      "ban_rate_weighted": 2.598
    },
    "Morgana": {
      "bans": 1567,
      "bans_weighted": 2383.0,
      "ban_rate": 4.9182,
      "ban_rate_weighted": 5.2114
    },
    "Camille": {
      "bans": 245,
      "bans_weighted": 349.0,
      "ban_rate": 0.769,
      "ban_rate_weighted": 0.7632
    },
    "Evelynn": {
      "bans": 1171,
      "bans_weighted": 1656.0,
      "ban_rate": 3.6753,
      "ban_rate_weighted": 3.6215
    },
    "Aatrox": {
      "bans": 1914,
      "bans_weighted": 2710.0,
      "ban_rate": 6.0073,
      "ban_rate_weighted": 5.9265
    },
    "Soraka": {
      "bans": 2866,
      "bans_weighted": 4080.0,
      "ban_rate": 8.9953,
      "ban_rate_weighted": 8.9225
    },
    "Braum": {
      "bans": 642,
      "bans_weighted": 849.0,
      "ban_rate": 2.015,
      "ban_rate_weighted": 1.8567
    },
    "K'Sante": {
      "bans": 338,
      "bans_weighted": 467.0,
      "ban_rate": 1.0609,
      "ban_rate_weighted": 1.0213
    },
    "Sona": {
      "bans": 2958,
      "bans_weighted": 4509.0,
      "ban_rate": 9.2841,
      "ban_rate_weighted": 9.8607
    },
    "Shaco": {
      "bans": 5774,
      "bans_weighted": 8471.0,
      "ban_rate": 18.1225,
      "ban_rate_weighted": 18.5252
    },
    "Galio": {
      "bans": 554,
      "bans_weighted": 750.0,
      "ban_rate": 1.7388,
      "ban_rate_weighted": 1.6402
    },
    "Blitzcrank": {
      "bans": 1035,
      "bans_weighted": 1475.0,
      "ban_rate": 3.2485,
      "ban_rate_weighted": 3.2257
    },
    "Darius": {
      "bans": 3955,
      "bans_weighted": 5515.0,
      "ban_rate": 12.4133,
      "ban_rate_weighted": 12.0607
    },
    "Janna": {
      "bans": 391,
      "bans_weighted": 590.0,
      "ban_rate": 1.2272,
      "ban_rate_weighted": 1.2903
    },
    "Milio": {
      "bans": 2447,
      "bans_weighted": 3406.0,
      "ban_rate": 7.6802,
      "ban_rate_weighted": 7.4486
    },
    "Lee Sin": {
      "bans": 4646,
      "bans_weighted": 6984.0,
      "ban_rate": 14.5821,
      "ban_rate_weighted": 15.2733
    },
    "Ziggs": {
      "bans": 227,
      "bans_weighted": 316.0,
      "ban_rate": 0.7125,
      "ban_rate_weighted": 0.6911
    },
    "Miss Fortune": {
      "bans": 109,
      "bans_weighted": 133.0,
      "ban_rate": 0.3421,
      "ban_rate_weighted": 0.2909
    },
    "Viego": {
      "bans": 995,
      "bans_weighted": 1319.0,
      "ban_rate": 3.1229,
      "ban_rate_weighted": 2.8845
    },
    "Azir": {
      "bans": 184,
      "bans_weighted": 249.0,
      "ban_rate": 0.5775,
      "ban_rate_weighted": 0.5445
    },
    "Twitch": {
      "bans": 945,
      "bans_weighted": 1335.0,
      "ban_rate": 2.966,
      "ban_rate_weighted": 2.9195
    },
    "Akshan": {
      "bans": 897,
      "bans_weighted": 1291.0,
      "ban_rate": 2.8154,
      "ban_rate_weighted": 2.8233
    },
    "Nilah": {
      "bans": 686,
      "bans_weighted": 958.0,
      "ban_rate": 2.1531,
      "ban_rate_weighted": 2.095
    },
    "Kennen": {
      "bans": 752,
      "bans_weighted": 1109.0,
      "ban_rate": 2.3603,
      "ban_rate_weighted": 2.4253
    },
    "Yone": {
      "bans": 1120,
      "bans_weighted": 1596.0,
      "ban_rate": 3.5153,
      "ban_rate_weighted": 3.4903
    },
    "Orianna": {
      "bans": 1059,
      "bans_weighted": 1621.0,
      "ban_rate": 3.3238,
      "ban_rate_weighted": 3.545
    },
    "Gangplank": {
      "bans": 601,
      "bans_weighted": 767.0,
      "ban_rate": 1.8863,
      "ban_rate_weighted": 1.6773
    },
    "Seraphine": {
      "bans": 212,
      "bans_weighted": 303.0,
      "ban_rate": 0.6654,
      "ban_rate_weighted": 0.6626
    },
    "Graves": {
      "bans": 255,
      "bans_weighted": 477.0,
      "ban_rate": 0.8004,
      "ban_rate_weighted": 1.0431
    },
    "Anivia": {
      "bans": 563,
      "bans_weighted": 806.0,
      "ban_rate": 1.7671,
      "ban_rate_weighted": 1.7626
    },
    "Sion": {
      "bans": 137,
      "bans_weighted": 212.0,
      "ban_rate": 0.43,
      "ban_rate_weighted": 0.4636
    },
    "Ezreal": {
      "bans": 2104,
      "bans_weighted": 2938.0,
      "ban_rate": 6.6037,
      "ban_rate_weighted": 6.4251
    },
    "Alistar": {
      "bans": 1005,
      "bans_weighted": 1404.0,
      "ban_rate": 3.1543,
      "ban_rate_weighted": 3.0704
    },
    "Jarvan IV": {
      "bans": 453,
      "bans_weighted": 706.0,
      "ban_rate": 1.4218,
      "ban_rate_weighted": 1.5439
    },
    "Dr. Mundo": {
      "bans": 222,
      "bans_weighted": 339.0,
      "ban_rate": 0.6968,
      "ban_rate_weighted": 0.7414
    },
    "Rammus": {
      "bans": 1215,
      "bans_weighted": 1723.0,
      "ban_rate": 3.8134,
      "ban_rate_weighted": 3.768
    },
    "Elise": {
      "bans": 278,
      "bans_weighted": 367.0,
      "ban_rate": 0.8725,
      "ban_rate_weighted": 0.8026
    },
    "Malzahar": {
      "bans": 404,
      "bans_weighted": 562.0,
      "ban_rate": 1.268,
      "ban_rate_weighted": 1.229
    },
    "Naafiri": {
      "bans": 1564,
      "bans_weighted": 2066.0,
      "ban_rate": 4.9088,
      "ban_rate_weighted": 4.5181
    },
    "Udyr": {
      "bans": 2878,
      "bans_weighted": 4221.0,
      "ban_rate": 9.033,
      "ban_rate_weighted": 9.2309
    },
    "Yunara": {
      "bans": 5809,
      "bans_weighted": 6701.0,
      "ban_rate": 18.2323,
      "ban_rate_weighted": 14.6544
    },
    "Zac": {
      "bans": 689,
      "bans_weighted": 956.0,
      "ban_rate": 2.1625,
      "ban_rate_weighted": 2.0907
    },
    "Samira": {
      "bans": 649,
      "bans_weighted": 885.0,
      "ban_rate": 2.037,
      "ban_rate_weighted": 1.9354
    },
    "Caitlyn": {
      "bans": 2356,
      "bans_weighted": 3467.0,
      "ban_rate": 7.3946,
      "ban_rate_weighted": 7.582
    },
    "Syndra": {
      "bans": 467,
      "bans_weighted": 708.0,
      "ban_rate": 1.4657,
      "ban_rate_weighted": 1.5483
    },
    "Jinx": {
      "bans": 675,
      "bans_weighted": 1114.0,
      "ban_rate": 2.1186,
      "ban_rate_weighted": 2.4362
    },
    "Lissandra": {
      "bans": 61,
      "bans_weighted": 77.0,
      "ban_rate": 0.1915,
      "ban_rate_weighted": 0.1684
    },
    "Shen": {
      "bans": 139,
      "bans_weighted": 197.0,
      "ban_rate": 0.4363,
      "ban_rate_weighted": 0.4308
    },
    "Yuumi": {
      "bans": 569,
      "bans_weighted": 856.0,
      "ban_rate": 1.7859,
      "ban_rate_weighted": 1.872
    },
    "Zilean": {
      "bans": 475,
      "bans_weighted": 706.0,
      "ban_rate": 1.4909,
      "ban_rate_weighted": 1.5439
    },
    "Thresh": {
      "bans": 686,
      "bans_weighted": 936.0,
      "ban_rate": 2.1531,
      "ban_rate_weighted": 2.0469
    },
    "Vel'Koz": {
      "bans": 84,
      "bans_weighted": 123.0,
      "ban_rate": 0.2636,
      "ban_rate_weighted": 0.269
    },
    "Smolder": {
      "bans": 294,
      "bans_weighted": 374.0,
      "ban_rate": 0.9228,
      "ban_rate_weighted": 0.8179
    },
    "Xin Zhao": {
      "bans": 773,
      "bans_weighted": 1092.0,
      "ban_rate": 2.4262,
      "ban_rate_weighted": 2.3881
    },
    "Kindred": {
      "bans": 514,
      "bans_weighted": 723.0,
      "ban_rate": 1.6133,
      "ban_rate_weighted": 1.5811
    },
    "Ivern": {
      "bans": 306,
      "bans_weighted": 452.0,
      "ban_rate": 0.9604,
      "ban_rate_weighted": 0.9885
    },
    "Teemo": {
      "bans": 567,
      "bans_weighted": 791.0,
      "ban_rate": 1.7796,
      "ban_rate_weighted": 1.7298
    },
    "Rell": {
      "bans": 1125,
      "bans_weighted": 1396.0,
      "ban_rate": 3.531,
      "ban_rate_weighted": 3.0529
    },
    "Skarner": {
      "bans": 341,
      "bans_weighted": 501.0,
      "ban_rate": 1.0703,
      "ban_rate_weighted": 1.0956
    },
    "Trundle": {
      "bans": 253,
      "bans_weighted": 318.0,
      "ban_rate": 0.7941,
      "ban_rate_weighted": 0.6954
    },
    "Kog'Maw": {
      "bans": 515,
      "bans_weighted": 758.0,
      "ban_rate": 1.6164,
      "ban_rate_weighted": 1.6577
    },
    "Olaf": {
      "bans": 240,
      "bans_weighted": 370.0,
      "ban_rate": 0.7533,
      "ban_rate_weighted": 0.8091
    },
    "Taliyah": {
      "bans": 337,
      "bans_weighted": 459.0,
      "ban_rate": 1.0577,
      "ban_rate_weighted": 1.0038
    },
    "Ornn": {
      "bans": 30,
      "bans_weighted": 44.0,
      "ban_rate": 0.0942,
      "ban_rate_weighted": 0.0962
    },
    "Fizz": {
      "bans": 259,
      "bans_weighted": 358.0,
      "ban_rate": 0.8129,
      "ban_rate_weighted": 0.7829
    },
    "Cassiopeia": {
      "bans": 454,
      "bans_weighted": 632.0,
      "ban_rate": 1.4249,
      "ban_rate_weighted": 1.3821
    },
    "Varus": {
      "bans": 624,
      "bans_weighted": 783.0,
      "ban_rate": 1.9585,
      "ban_rate_weighted": 1.7123
    },
    "Hecarim": {
      "bans": 1324,
      "bans_weighted": 1819.0,
      "ban_rate": 4.1556,
      "ban_rate_weighted": 3.978
    },
    "Briar": {
      "bans": 308,
      "bans_weighted": 413.0,
      "ban_rate": 0.9667,
      "ban_rate_weighted": 0.9032
    },
    "Corki": {
      "bans": 643,
      "bans_weighted": 1011.0,
      "ban_rate": 2.0181,
      "ban_rate_weighted": 2.2109
    },
    "Nasus": {
      "bans": 315,
      "bans_weighted": 391.0,
      "ban_rate": 0.9887,
      "ban_rate_weighted": 0.8551
    },
    "Aurelion Sol": {
      "bans": 150,
      "bans_weighted": 235.0,
      "ban_rate": 0.4708,
      "ban_rate_weighted": 0.5139
    },
    "Neeko": {
      "bans": 639,
      "bans_weighted": 1041.0,
      "ban_rate": 2.0056,
      "ban_rate_weighted": 2.2766
    },
    "Nocturne": {
      "bans": 218,
      "bans_weighted": 290.0,
      "ban_rate": 0.6842,
      "ban_rate_weighted": 0.6342
    },
    "Zoe": {
      "bans": 601,
      "bans_weighted": 910.0,
      "ban_rate": 1.8863,
      "ban_rate_weighted": 1.9901
    },
    "Singed": {
      "bans": 121,
      "bans_weighted": 142.0,
      "ban_rate": 0.3798,
      "ban_rate_weighted": 0.3105
    },
    "Garen": {
      "bans": 373,
      "bans_weighted": 636.0,
      "ban_rate": 1.1707,
      "ban_rate_weighted": 1.3909
    },
    "Warwick": {
      "bans": 147,
      "bans_weighted": 187.0,
      "ban_rate": 0.4614,
      "ban_rate_weighted": 0.4089
    },
    "Diana": {
      "bans": 504,
      "bans_weighted": 778.0,
      "ban_rate": 1.5819,
      "ban_rate_weighted": 1.7014
    },
    "Gragas": {
      "bans": 342,
      "bans_weighted": 442.0,
      "ban_rate": 1.0734,
      "ban_rate_weighted": 0.9666
    },
    "Senna": {
      "bans": 244,
      "bans_weighted": 312.0,
      "ban_rate": 0.7658,
      "ban_rate_weighted": 0.6823
    },
    "Ahri": {
      "bans": 473,
      "bans_weighted": 684.0,
      "ban_rate": 1.4846,
      "ban_rate_weighted": 1.4958
    },
    "Lillia": {
      "bans": 352,
      "bans_weighted": 468.0,
      "ban_rate": 1.1048,
      "ban_rate_weighted": 1.0235
    },
    "Rek'Sai": {
      "bans": 217,
      "bans_weighted": 273.0,
      "ban_rate": 0.6811,
      "ban_rate_weighted": 0.597
    },
    "Annie": {
      "bans": 105,
      "bans_weighted": 142.0,
      "ban_rate": 0.3296,
      "ban_rate_weighted": 0.3105
    },
    "Tryndamere": {
      "bans": 135,
      "bans_weighted": 189.0,
      "ban_rate": 0.4237,
      "ban_rate_weighted": 0.4133
    },
    "Rumble": {
      "bans": 261,
      "bans_weighted": 385.0,
      "ban_rate": 0.8192,
      "ban_rate_weighted": 0.842
    },
    "Vex": {
      "bans": 220,
      "bans_weighted": 290.0,
      "ban_rate": 0.6905,
      "ban_rate_weighted": 0.6342
    },
    "Shyvana": {
      "bans": 40,
      "bans_weighted": 67.0,
      "ban_rate": 0.1255,
      "ban_rate_weighted": 0.1465
    },
    "Zyra": {
      "bans": 239,
      "bans_weighted": 358.0,
      "ban_rate": 0.7501,
      "ban_rate_weighted": 0.7829
    },
    "Sett": {
      "bans": 357,
      "bans_weighted": 491.0,
      "ban_rate": 1.1205,
      "ban_rate_weighted": 1.0738
    },
    "Xerath": {
      "bans": 187,
      "bans_weighted": 247.0,
      "ban_rate": 0.5869,
      "ban_rate_weighted": 0.5402
    },
    "Zeri": {
      "bans": 70,
      "bans_weighted": 78.0,
      "ban_rate": 0.2197,
      "ban_rate_weighted": 0.1706
    },
    "Viktor": {
      "bans": 403,
      "bans_weighted": 546.0,
      "ban_rate": 1.2649,
      "ban_rate_weighted": 1.194
    },
    "Brand": {
      "bans": 73,
      "bans_weighted": 100.0,
      "ban_rate": 0.2291,
      "ban_rate_weighted": 0.2187
    },
    "Illaoi": {
      "bans": 177,
      "bans_weighted": 233.0,
      "ban_rate": 0.5555,
      "ban_rate_weighted": 0.5095
    },
    "Heimerdinger": {
      "bans": 73,
      "bans_weighted": 122.0,
      "ban_rate": 0.2291,
      "ban_rate_weighted": 0.2668
    },
    "Vi": {
      "bans": 129,
      "bans_weighted": 165.0,
      "ban_rate": 0.4049,
      "ban_rate_weighted": 0.3608
    },
    "Kled": {
      "bans": 84,
      "bans_weighted": 121.0,
      "ban_rate": 0.2636,
      "ban_rate_weighted": 0.2646
    },
    "Gnar": {
      "bans": 202,
      "bans_weighted": 251.0,
      "ban_rate": 0.634,
      "ban_rate_weighted": 0.5489
    },
    "Nunu e Willump": {
      "bans": 247,
      "bans_weighted": 390.0,
      "ban_rate": 0.7752,
      "ban_rate_weighted": 0.8529
    },
    "Ryze": {
      "bans": 594,
      "bans_weighted": 964.0,
      "ban_rate": 1.8643,
      "ban_rate_weighted": 2.1082
    },
    "Veigar": {
      "bans": 69,
      "bans_weighted": 97.0,
      "ban_rate": 0.2166,
      "ban_rate_weighted": 0.2121
    },
    "Xayah": {
      "bans": 113,
      "bans_weighted": 144.0,
      "ban_rate": 0.3547,
      "ban_rate_weighted": 0.3149
    },
    "Sejuani": {
      "bans": 25,
      "bans_weighted": 35.0,
      "ban_rate": 0.0785,
      "ban_rate_weighted": 0.0765
    },
    "Cho'Gath": {
      "bans": 161,
      "bans_weighted": 267.0,
      "ban_rate": 0.5053,
      "ban_rate_weighted": 0.5839
    },
    "Swain": {
      "bans": 68,
      "bans_weighted": 109.0,
      "ban_rate": 0.2134,
      "ban_rate_weighted": 0.2384
    },
    "Jhin": {
      "bans": 136,
      "bans_weighted": 185.0,
      "ban_rate": 0.4269,
      "ban_rate_weighted": 0.4046
    },
    "Tristana": {
      "bans": 98,
      "bans_weighted": 121.0,
      "ban_rate": 0.3076,
      "ban_rate_weighted": 0.2646
    },
    "Taric": {
      "bans": 53,
      "bans_weighted": 92.0,
      "ban_rate": 0.1663,
      "ban_rate_weighted": 0.2012
    },
    "Kalista": {
      "bans": 201,
      "bans_weighted": 288.0,
      "ban_rate": 0.6309,
      "ban_rate_weighted": 0.6298
    },
    "Rakan": {
      "bans": 122,
      "bans_weighted": 161.0,
      "ban_rate": 0.3829,
      "ban_rate_weighted": 0.3521
    },
    "Tahm Kench": {
      "bans": 28,
      "bans_weighted": 39.0,
      "ban_rate": 0.0879,
      "ban_rate_weighted": 0.0853
    },
    "Amumu": {
      "bans": 56,
      "bans_weighted": 78.0,
      "ban_rate": 0.1758,
      "ban_rate_weighted": 0.1706
    },
    "Renata Glasc": {
      "bans": 20,
      "bans_weighted": 27.0,
      "ban_rate": 0.0628,
      "ban_rate_weighted": 0.059
    },
    "Twisted Fate": {
      "bans": 50,
      "bans_weighted": 70.0,
      "ban_rate": 0.1569,
      "ban_rate_weighted": 0.1531
    },
    "Maokai": {
      "bans": 9,
      "bans_weighted": 13.0,
      "ban_rate": 0.0282,
      "ban_rate_weighted": 0.0284
    }
  },
  "_metadata": {
    "recent_window_start": "2025-10-02T02:01:09.038000+00:00",
    "previous_window_start": "2025-09-02T02:01:09.038000+00:00",
    "latest_match_timestamp": "2025-11-01T02:01:09.038000+00:00",
    "weights": {
      "recent_days": 30,
      "recent_weight": 2.0,
      "previous_weight": 1.0,
      "older_weight": 1.0
    },
    "target_tiers": [
      "DIAMOND",
      "MASTER",
      "GRANDMASTER",
      "CHALLENGER"
    ]
  }
}